paystack/__init__.py
paystack/admin.py
paystack/apps.py
paystack/models.py
paystack/paystack_urls.py
paystack/urls.py
paystack/utils.py
paystack/migrations/0001_initial.py
paystack/migrations/__init__.py
paystack/serializers/__init__.py
paystack/serializers/customer.py
paystack/serializers/transaction.py
paystack/services/__init__.py
paystack/services/base_api_service.py
paystack/services/customer_service.py
paystack/services/transaction_service.py
paystack/services/webhook_service.py
paystack/views/__init__.py
paystack/views/customer.py
paystack/views/transaction.py
paystack/views/webhook.py
django_rest_paystack-2.2.2.dist-info/LICENSE
django_rest_paystack-2.2.2.dist-info/METADATA
django_rest_paystack-2.2.2.dist-info/WHEEL
django_rest_paystack-2.2.2.dist-info/top_level.txt
django_rest_paystack-2.2.2.dist-info/RECORD
