Metadata-Version: 2.1
Name: django-rest-paystack
Version: 2.2.2
Summary: A minimal SDK for integrating Paystack into your django-rest API backend.
Home-page: https://github.com/Nyior/django-rest-paystack
Author: Nyior Clement
Author-email: cnyior27@gmail.com
License: MIT
Project-URL: Bug Tracker, https://github.com/Nyior/django-rest-paystack/issues
Project-URL: Source Code, https://github.com/Nyior/django-rest-paystack
Keywords: django,rest,api,paystack,rest-framework,payment,initialize payment,verify payment,charge authorization,handle webhook
Platform: UNKNOWN
Classifier: Environment :: Web Environment
Classifier: Framework :: Django
Classifier: Framework :: Django :: 2.0
Classifier: Framework :: Django :: 3.0
Classifier: Intended Audience :: Developers
Classifier: License :: OSI Approved :: MIT License
Classifier: Operating System :: OS Independent
Classifier: Programming Language :: Python
Classifier: Programming Language :: Python :: 3
Classifier: Programming Language :: Python :: 3 :: Only
Classifier: Topic :: Internet
Classifier: Topic :: Internet :: WWW/HTTP
Requires-Python: >=3.7
License-File: LICENSE
